setup.cfg
setup.py
testcli/__init__.py
testcli.egg-info/PKG-INFO
testcli.egg-info/SOURCES.txt
testcli.egg-info/dependency_links.txt
testcli.egg-info/entry_points.txt
testcli.egg-info/requires.txt
testcli.egg-info/top_level.txt