Metadata-Version: 1.1
Name: testcli
Version: 0.1.0
Summary: testclitool
Home-page: https://nadh.in
Author: aynranddog
Author-email: aynranddog@gmail.com
License: MIT
Download-URL: https://github.com/aynranddog/asdf
Platform: UNKNOWN
